{
  "userId": 2258623929,
  "displayName": "1of1DOLO",
  "status": "in-game",
  "placeId": 135202704953082,
  "jobId": "139fbe50-4022-4438-b246-b53bb8a86c6b",
  "join": "roblox://placeId=135202704953082&gameInstanceId=139fbe50-4022-4438-b246-b53bb8a86c6b",
  "follow": "roblox://followUserId=2258623929",
  "web": "https://www.roblox.com/games/start?placeId=135202704953082&gameInstanceId=139fbe50-4022-4438-b246-b53bb8a86c6b",
  "location": "🚗COLLECTOR! Car Dealership Tycoon",
  "updatedAt": 1770170147849
}
