{
  "userId": 2258623929,
  "displayName": "1of1DOLO",
  "status": "in-game",
  "placeId": 135202704953082,
  "jobId": "46838282-2a4b-4b07-bc11-2db6b3e30a2c",
  "join": "roblox://placeId=135202704953082&gameInstanceId=46838282-2a4b-4b07-bc11-2db6b3e30a2c",
  "follow": "roblox://followUserId=2258623929",
  "web": "https://www.roblox.com/games/start?placeId=135202704953082&gameInstanceId=46838282-2a4b-4b07-bc11-2db6b3e30a2c",
  "location": "🏈 BIG GAME! Car Dealership Tycoon",
  "updatedAt": 1770692996946
}
