{
  "userId": 2405330634,
  "displayName": "emiryokus07",
  "status": "in-game",
  "placeId": 94217045453265,
  "jobId": "ccef8061-dfc8-4cb9-80f0-2134096c1a5e",
  "join": "roblox://placeId=94217045453265&gameInstanceId=ccef8061-dfc8-4cb9-80f0-2134096c1a5e",
  "follow": "roblox://followUserId=2405330634",
  "web": "https://www.roblox.com/games/start?placeId=94217045453265&gameInstanceId=ccef8061-dfc8-4cb9-80f0-2134096c1a5e",
  "location": "[🥊GAUNTLETS] Dueling Grounds ⚔️ ",
  "updatedAt": 1764413919181
}
