{
  "userId": 2495320179,
  "displayName": "MasJawa",
  "status": "in-game",
  "placeId": 79546208627805,
  "jobId": "f794083d-4c18-4483-8b0b-5b019bb0d867",
  "join": "roblox://placeId=79546208627805&gameInstanceId=f794083d-4c18-4483-8b0b-5b019bb0d867",
  "follow": "roblox://followUserId=2495320179",
  "web": "https://www.roblox.com/games/start?placeId=79546208627805&gameInstanceId=f794083d-4c18-4483-8b0b-5b019bb0d867",
  "location": "[💥] 99 Nights in the Forest 🔦",
  "updatedAt": 1771080696279
}
