{
  "userId": 2495320179,
  "displayName": "MasJawa",
  "status": "in-game",
  "placeId": 126509999114328,
  "jobId": "b759a53b-136b-4eb0-aada-50129e793bb3",
  "join": "roblox://placeId=126509999114328&gameInstanceId=b759a53b-136b-4eb0-aada-50129e793bb3",
  "follow": "roblox://followUserId=2495320179",
  "web": "https://www.roblox.com/games/start?placeId=126509999114328&gameInstanceId=b759a53b-136b-4eb0-aada-50129e793bb3",
  "location": "[💘] 99 Nights in the Forest 🔦",
  "updatedAt": 1771472287661
}
