{
  "userId": 3181292178,
  "displayName": "NotoriousKal",
  "status": "in-game",
  "placeId": 136764190843219,
  "jobId": "d7e129db-7e5f-49f3-aad0-198577224099",
  "join": "roblox://placeId=136764190843219&gameInstanceId=d7e129db-7e5f-49f3-aad0-198577224099",
  "follow": "roblox://followUserId=3181292178",
  "web": "https://www.roblox.com/games/start?placeId=136764190843219&gameInstanceId=d7e129db-7e5f-49f3-aad0-198577224099",
  "location": "[UPD] Knockout! 🐧",
  "updatedAt": 1770502642392
}
