{
  "userId": 3383246600,
  "displayName": "PX_ AssassinCROW",
  "status": "in-game",
  "placeId": 122659178380202,
  "jobId": "e1b1ecb9-3c01-47a2-a0c6-3bc2d23438e1",
  "join": "roblox://placeId=122659178380202&gameInstanceId=e1b1ecb9-3c01-47a2-a0c6-3bc2d23438e1",
  "follow": "roblox://followUserId=3383246600",
  "web": "https://www.roblox.com/games/start?placeId=122659178380202&gameInstanceId=e1b1ecb9-3c01-47a2-a0c6-3bc2d23438e1",
  "location": "[✨] PLS DONATE MODDED 💸",
  "updatedAt": 1764879280805
}
