{
  "userId": 3383246600,
  "displayName": "PX_ AssassinCROW",
  "status": "in-game",
  "placeId": 15550215902,
  "jobId": "7caef4f1-f7a2-488b-85ec-04652810bb76",
  "join": "roblox://placeId=15550215902&gameInstanceId=7caef4f1-f7a2-488b-85ec-04652810bb76",
  "follow": "roblox://followUserId=3383246600",
  "web": "https://www.roblox.com/games/start?placeId=15550215902&gameInstanceId=7caef4f1-f7a2-488b-85ec-04652810bb76",
  "location": "[🎵 1300+ SONGS!] Sing It! Karaoke Battles [VC🎤]",
  "updatedAt": 1765517875069
}
