{
  "userId": 3383246600,
  "displayName": "PX_ AssassinCROW",
  "status": "in-game",
  "placeId": 134425882559799,
  "jobId": "008de42d-26e0-4751-95d3-219456341d4c",
  "join": "roblox://placeId=134425882559799&gameInstanceId=008de42d-26e0-4751-95d3-219456341d4c",
  "follow": "roblox://followUserId=3383246600",
  "web": "https://www.roblox.com/games/start?placeId=134425882559799&gameInstanceId=008de42d-26e0-4751-95d3-219456341d4c",
  "location": "Guide The Bacons",
  "updatedAt": 1770449243672
}
