{
  "userId": 3524437881,
  "displayName": "Xx_T4GGYxXxODLeader",
  "status": "in-game",
  "placeId": 3260590327,
  "jobId": "733501fb-63bc-49dd-97df-c2612bbf70a1",
  "join": "roblox://placeId=3260590327&gameInstanceId=733501fb-63bc-49dd-97df-c2612bbf70a1",
  "follow": "roblox://followUserId=3524437881",
  "web": "https://www.roblox.com/games/start?placeId=3260590327&gameInstanceId=733501fb-63bc-49dd-97df-c2612bbf70a1",
  "location": "[💵 KINGPIN]  Tower Defense Simulator",
  "updatedAt": 1784403291600
}
