{
  "userId": 3524437881,
  "displayName": "Xx_T4GGYxXxODLeader",
  "status": "in-game",
  "placeId": 5591597781,
  "jobId": "7ab1514f-1360-4e17-9afb-6bdf5ec3a6aa",
  "join": "roblox://placeId=5591597781&gameInstanceId=7ab1514f-1360-4e17-9afb-6bdf5ec3a6aa",
  "follow": "roblox://followUserId=3524437881",
  "web": "https://www.roblox.com/games/start?placeId=5591597781&gameInstanceId=7ab1514f-1360-4e17-9afb-6bdf5ec3a6aa",
  "location": "[💵 KINGPIN]  Tower Defense Simulator",
  "updatedAt": 1784643595212
}
