{
  "userId": 4139827928,
  "displayName": "JzKommtTravis",
  "status": "in-game",
  "placeId": 81020033883861,
  "jobId": "742edbf0-0394-4fc5-863f-4bb5c27a7188",
  "join": "roblox://placeId=81020033883861&gameInstanceId=742edbf0-0394-4fc5-863f-4bb5c27a7188",
  "follow": "roblox://followUserId=4139827928",
  "web": "https://www.roblox.com/games/start?placeId=81020033883861&gameInstanceId=742edbf0-0394-4fc5-863f-4bb5c27a7188",
  "location": "[🌵UPDATE] 🚗 Highway Showdown",
  "updatedAt": 1770312190599
}
