{
  "userId": 4309598145,
  "displayName": "Fear_ALONE",
  "status": "in-game",
  "placeId": 124311897657957,
  "jobId": "86462a0a-233a-4a3b-a66b-4d31b0c11876",
  "join": "roblox://placeId=124311897657957&gameInstanceId=86462a0a-233a-4a3b-a66b-4d31b0c11876",
  "follow": "roblox://followUserId=4309598145",
  "web": "https://www.roblox.com/games/start?placeId=124311897657957&gameInstanceId=86462a0a-233a-4a3b-a66b-4d31b0c11876",
  "location": "⛏️ Break a Lucky Block!",
  "updatedAt": 1771659758855
}
