{
  "userId": 4383361224,
  "displayName": "Delusional",
  "status": "in-game",
  "placeId": 106809703371658,
  "jobId": "1c462ebb-da07-40c1-b428-92e5d47464cd",
  "join": "roblox://placeId=106809703371658&gameInstanceId=1c462ebb-da07-40c1-b428-92e5d47464cd",
  "follow": "roblox://followUserId=4383361224",
  "web": "https://www.roblox.com/games/start?placeId=106809703371658&gameInstanceId=1c462ebb-da07-40c1-b428-92e5d47464cd",
  "location": "[🎵] Project : RUSHER",
  "updatedAt": 1764782272190
}
