{
  "userId": 5075616449,
  "displayName": "MLXU",
  "status": "in-game",
  "placeId": 139217467707445,
  "jobId": "4aa83f86-f3fb-4680-8ec5-b05723a8fa1a",
  "join": "roblox://placeId=139217467707445&gameInstanceId=4aa83f86-f3fb-4680-8ec5-b05723a8fa1a",
  "follow": "roblox://followUserId=5075616449",
  "web": "https://www.roblox.com/games/start?placeId=139217467707445&gameInstanceId=4aa83f86-f3fb-4680-8ec5-b05723a8fa1a",
  "location": "Steal Brainrots Trading Plaza 🛒",
  "updatedAt": 1770166848999
}
