{
  "userId": 5075616449,
  "displayName": "MLXU",
  "status": "in-game",
  "placeId": 139217467707445,
  "jobId": "a4cf6e8d-908e-4dfd-b12e-84ea05623c97",
  "join": "roblox://placeId=139217467707445&gameInstanceId=a4cf6e8d-908e-4dfd-b12e-84ea05623c97",
  "follow": "roblox://followUserId=5075616449",
  "web": "https://www.roblox.com/games/start?placeId=139217467707445&gameInstanceId=a4cf6e8d-908e-4dfd-b12e-84ea05623c97",
  "location": "Steal Brainrots Trading Plaza 🛒",
  "updatedAt": 1771281311059
}
