{
  "userId": 5075616449,
  "displayName": "MLXU",
  "status": "in-game",
  "placeId": 139217467707445,
  "jobId": "b38b6291-fdaf-4fe5-90cd-d2a181c52923",
  "join": "roblox://placeId=139217467707445&gameInstanceId=b38b6291-fdaf-4fe5-90cd-d2a181c52923",
  "follow": "roblox://followUserId=5075616449",
  "web": "https://www.roblox.com/games/start?placeId=139217467707445&gameInstanceId=b38b6291-fdaf-4fe5-90cd-d2a181c52923",
  "location": "Steal Brainrots Trading Plaza 🛒",
  "updatedAt": 1771207448773
}
