{
  "userId": 687752243,
  "displayName": "HERO_Kratos",
  "status": "in-game",
  "placeId": 3351674303,
  "jobId": "c7976f3f-d3fa-4df1-b8c5-624d19ab68bc",
  "join": "roblox://placeId=3351674303&gameInstanceId=c7976f3f-d3fa-4df1-b8c5-624d19ab68bc",
  "follow": "roblox://followUserId=687752243",
  "web": "https://www.roblox.com/games/start?placeId=3351674303&gameInstanceId=c7976f3f-d3fa-4df1-b8c5-624d19ab68bc",
  "location": "[LIMITED & BODYKITS] Driving Empire🏎️ Car Racing",
  "updatedAt": 1770683217039
}
