{
  "userId": 7025658862,
  "displayName": "SEN_xL3G3NDSx",
  "status": "in-game",
  "placeId": 137826330724902,
  "jobId": "f6b8b3a3-950f-4424-aaf7-14de8f7232a1",
  "join": "roblox://placeId=137826330724902&gameInstanceId=f6b8b3a3-950f-4424-aaf7-14de8f7232a1",
  "follow": "roblox://followUserId=7025658862",
  "web": "https://www.roblox.com/games/start?placeId=137826330724902&gameInstanceId=f6b8b3a3-950f-4424-aaf7-14de8f7232a1",
  "location": "Scary Shawarma Kiosk: the ANOMALY [horror]",
  "updatedAt": 1771657510697
}
