{
  "userId": 8078846359,
  "displayName": "XxDaniellordexX",
  "status": "in-game",
  "placeId": 3475422608,
  "jobId": "f0508f08-77f0-42e8-9e5c-8a8d5a8faebf",
  "join": "roblox://placeId=3475422608&gameInstanceId=f0508f08-77f0-42e8-9e5c-8a8d5a8faebf",
  "follow": "roblox://followUserId=8078846359",
  "web": "https://www.roblox.com/games/start?placeId=3475422608&gameInstanceId=f0508f08-77f0-42e8-9e5c-8a8d5a8faebf",
  "location": "[NEW SZN 1] Dragon Adventures 🐉",
  "updatedAt": 1768529583470
}
