{
  "userId": 8078846359,
  "displayName": "XxDaniellordexX",
  "status": "in-game",
  "placeId": 93635039874468,
  "jobId": "de2b2f57-fa3f-49d2-9933-b932b45a5d9d",
  "join": "roblox://placeId=93635039874468&gameInstanceId=de2b2f57-fa3f-49d2-9933-b932b45a5d9d",
  "follow": "roblox://followUserId=8078846359",
  "web": "https://www.roblox.com/games/start?placeId=93635039874468&gameInstanceId=de2b2f57-fa3f-49d2-9933-b932b45a5d9d",
  "location": "Burger Shack 🍔 [HORROR]",
  "updatedAt": 1764871615547
}
