{
  "userId": 8315231560,
  "displayName": "YZ_ISoloAli",
  "status": "in-game",
  "placeId": 134709311234986,
  "jobId": "f282ca31-d486-45dc-aebf-f220651c9749",
  "join": "roblox://placeId=134709311234986&gameInstanceId=f282ca31-d486-45dc-aebf-f220651c9749",
  "follow": "roblox://followUserId=8315231560",
  "web": "https://www.roblox.com/games/start?placeId=134709311234986&gameInstanceId=f282ca31-d486-45dc-aebf-f220651c9749",
  "location": "[💥] TNT Incremental",
  "updatedAt": 1770737217128
}
